etiket/__init__.py
etiket/_release_notes.txt
etiket/logging.py
etiket/main.py
etiket/settings.py
etiket/db/__init__.py
etiket/db/get_db_session.py
etiket/db/models.py
etiket/db/types.py
etiket/db/alembic/README
etiket/db/alembic/env.py
etiket/db/alembic/script.py.mako
etiket/db/alembic/versions/041b93186c29_update_version_nameming_in_database.py
etiket/db/alembic/versions/0ba314714736_add_datetime_with_timezones.py
etiket/db/alembic/versions/12679c2891d7_add_index_to_dataset_id_column_in_files_.py
etiket/db/alembic/versions/1c77427f1d45_added_version_tables.py
etiket/db/alembic/versions/32e737572c18_ix_search_helper_tsvector.py
etiket/db/alembic/versions/37e90d5a09bb_etiket_v_0_1_1.py
etiket/db/alembic/versions/45d0efbe7912_add_userlog_table.py
etiket/db/alembic/versions/53270e68eafa_update_datetime_of_files_to_utc_time.py
etiket/db/alembic/versions/58562ef411b3_add_unknown_type_setting.py
etiket/db/alembic/versions/675fac985b76_add_index_on_scope_id_column.py
etiket/db/alembic/versions/71e0bcc916d6_update_file_table_with_upload_id_and_.py
etiket/db/alembic/versions/82b1d0215470_fix_datatype.py
etiket/db/alembic/versions/897f64d16463_update_uniqueness_of_alt_uuid.py
etiket/db/alembic/versions/a2fc6a2ffa1a_added_more_permissions_for_buckets.py
etiket/db/alembic/versions/a3746779e162_adding_extra_field_to_files.py
etiket/db/alembic/versions/a67f3eec9109_added_s3_management.py
etiket/db/alembic/versions/a68eec19c8b6_fixing_more_small_errors.py
etiket/db/alembic/versions/b4036882599e_fix_naming.py
etiket/db/alembic/versions/be954725414b_add_md5_checksums.py
etiket/db/alembic/versions/c14b4c83c043_update_updating_types.py
etiket/db/alembic/versions/d39215e04acd_update_unique_contraint.py
etiket/db/alembic/versions/d5787aaedbf7_adding_some_extra_fields.py
etiket/db/alembic/versions/d6f4df128cd5_add_missing_columns.py
etiket/db/alembic/versions/dd655830f014_version_0_2_0_database_schema.py
etiket/db/alembic/versions/e0b7bbbca868_update_version_id_to_bigint.py
etiket-0.1.5.dist-info/METADATA
etiket-0.1.5.dist-info/WHEEL
etiket-0.1.5.dist-info/top_level.txt
etiket-0.1.5.dist-info/RECORD
